taskiq_aio_pika/__init__.py
taskiq_aio_pika/broker.py
taskiq_aio_pika/py.typed
taskiq_aio_pika-0.4.4.dist-info/METADATA
taskiq_aio_pika-0.4.4.dist-info/WHEEL
taskiq_aio_pika-0.4.4.dist-info/licenses/LICENSE
taskiq_aio_pika-0.4.4.dist-info/RECORD
