Metadata-Version: 2.4
Name: taskiq-aio-pika
Version: 0.4.4
Summary: RabbitMQ broker for taskiq
License: LICENSE
License-File: LICENSE
Keywords: taskiq,tasks,distributed,async,aio-pika
Author: Pavel Kirilin
Author-email: win10@list.ru
Requires-Python: >=3.8.1,<4.0.0
Classifier: License :: Other/Proprietary License
Classifier: Programming Language :: Python
Classifier: Programming Language :: Python :: 3
Classifier: Programming Language :: Python :: 3.9
Classifier: Programming Language :: Python :: 3.10
Classifier: Programming Language :: Python :: 3.11
Classifier: Programming Language :: Python :: 3.12
Classifier: Programming Language :: Python :: 3.13
Classifier: Programming Language :: Python :: 3.14
Classifier: Programming Language :: Python :: 3 :: Only
Classifier: Programming Language :: Python :: 3.8
Classifier: Typing :: Typed
Requires-Dist: aio-pika (>=9.0,<10.0)
Requires-Dist: taskiq (>=0.6.0,<1)
Project-URL: Homepage, https://github.com/taskiq-python/taskiq-aio-pika
Project-URL: Repository, https://github.com/taskiq-python/taskiq-aio-pika
